<?xml version="1.0" encoding="UTF-8"?>
<build-type xmlns:xsi="http://www.w3.org/2001/XMLSchema-instance" uuid="b55498d0-d0a1-48f1-88fb-0b4a53287e12" xsi:noNamespaceSchemaLocation="http://www.jetbrains.com/teamcity/schemas/2018.1/project-config.xsd">
  <name>Build1</name>
  <description />
  <settings>
    <options>
      <option name="artifactRules" value="**\* =&gt; %confparam1%.zip" />
      <option name="checkoutMode" value="ON_SERVER" />
    </options>
    <parameters>
      <param name="confparam1" value="%build.number%" />
    </parameters>
    <build-runners />
    <vcs-settings>
      <vcs-entry-ref root-id="Root1" />
    </vcs-settings>
    <requirements />
    <build-triggers />
    <cleanup />
  </settings>
</build-type>

