<?xml version="1.0" encoding="UTF-8"?>
<build-type xmlns:xsi="http://www.w3.org/2001/XMLSchema-instance" uuid="377d36a8-ccc5-46c9-8356-9ac6d315a9b0" xsi:noNamespaceSchemaLocation="http://www.jetbrains.com/teamcity/schemas/2018.1/project-config.xsd">
  <name>BuildB</name>
  <description />
  <settings ref="Dependencies_BrokenDependenciesReport_BuildBTemplate">
    <parameters />
    <build-runners />
    <vcs-settings />
    <requirements />
    <build-triggers />
    <cleanup />
  </settings>
</build-type>

